{
  "meta": {
    "provenance": "mathlib5/sorrydb/metadata.json (MATHLIB5-20260710-SORRYDB-001)",
    "id": "INTERCAL-SCHOOL-SORRY-ROSTER",
    "count": 300,
    "note": "Full 300+ sorry corpus restored from sorrydb export; assign to certified graduates."
  },
  "targets": [
    {
      "source": "mathlib5/sorrydb",
      "status": "unproven",
      "family": "audit",
      "id": "SORRY-001",
      "note": "close via 3-witness consensus (NT+ALG+IT)"
    },
    {
      "source": "mathlib5/sorrydb",
      "status": "unproven",
      "family": "audit",
      "id": "SORRY-002",
      "note": "close via 3-witness consensus (NT+ALG+IT)"
    },
    {
      "source": "mathlib5/sorrydb",
      "status": "unproven",
      "family": "audit",
      "id": "SORRY-003",
      "note": "close via 3-witness consensus (NT+ALG+IT)"
    },
    {
      "source": "mathlib5/sorrydb",
      "status": "unproven",
      "family": "audit",
      "id": "SORRY-004",
      "note": "close via 3-witness consensus (NT+ALG+IT)"
    },
    {
      "source": "mathlib5/sorrydb",
      "status": "unproven",
      "family": "audit",
      "id": "SORRY-005",
      "note": "close via 3-witness consensus (NT+ALG+IT)"
    },
    {
      "source": "mathlib5/sorrydb",
      "status": "unproven",
      "family": "audit",
      "id": "SORRY-006",
      "note": "close via 3-witness consensus (NT+ALG+IT)"
    },
    {
      "source": "mathlib5/sorrydb",
      "status": "unproven",
      "family": "audit",
      "id": "SORRY-007",
      "note": "close via 3-witness consensus (NT+ALG+IT)"
    },
    {
      "source": "mathlib5/sorrydb",
      "status": "unproven",
      "family": "audit",
      "id": "SORRY-008",
      "note": "close via 3-witness consensus (NT+ALG+IT)"
    },
    {
      "source": "mathlib5/sorrydb",
      "status": "unproven",
      "family": "audit",
      "id": "SORRY-009",
      "note": "close via 3-witness consensus (NT+ALG+IT)"
    },
    {
      "source": "mathlib5/sorrydb",
      "status": "unproven",
      "family": "audit",
      "id": "SORRY-010",
      "note": "close via 3-witness consensus (NT+ALG+IT)"
    },
    {
      "source": "mathlib5/sorrydb",
      "status": "unproven",
      "family": "audit",
      "id": "SORRY-011",
      "note": "close via 3-witness consensus (NT+ALG+IT)"
    },
    {
      "source": "mathlib5/sorrydb",
      "status": "unproven",
      "family": "audit",
      "id": "SORRY-012",
      "note": "close via 3-witness consensus (NT+ALG+IT)"
    },
    {
      "source": "mathlib5/sorrydb",
      "status": "unproven",
      "family": "audit",
      "id": "SORRY-013",
      "note": "close via 3-witness consensus (NT+ALG+IT)"
    },
    {
      "source": "mathlib5/sorrydb",
      "status": "unproven",
      "family": "audit",
      "id": "SORRY-014",
      "note": "close via 3-witness consensus (NT+ALG+IT)"
    },
    {
      "source": "mathlib5/sorrydb",
      "status": "unproven",
      "family": "audit",
      "id": "SORRY-015",
      "note": "close via 3-witness consensus (NT+ALG+IT)"
    },
    {
      "source": "mathlib5/sorrydb",
      "status": "unproven",
      "family": "audit",
      "id": "SORRY-016",
      "note": "close via 3-witness consensus (NT+ALG+IT)"
    },
    {
      "source": "mathlib5/sorrydb",
      "status": "unproven",
      "family": "audit",
      "id": "SORRY-017",
      "note": "close via 3-witness consensus (NT+ALG+IT)"
    },
    {
      "source": "mathlib5/sorrydb",
      "status": "unproven",
      "family": "audit",
      "id": "SORRY-018",
      "note": "close via 3-witness consensus (NT+ALG+IT)"
    },
    {
      "source": "mathlib5/sorrydb",
      "status": "unproven",
      "family": "audit",
      "id": "SORRY-019",
      "note": "close via 3-witness consensus (NT+ALG+IT)"
    },
    {
      "source": "mathlib5/sorrydb",
      "status": "unproven",
      "family": "audit",
      "id": "SORRY-020",
      "note": "close via 3-witness consensus (NT+ALG+IT)"
    },
    {
      "source": "mathlib5/sorrydb",
      "status": "unproven",
      "family": "audit",
      "id": "SORRY-021",
      "note": "close via 3-witness consensus (NT+ALG+IT)"
    },
    {
      "source": "mathlib5/sorrydb",
      "status": "unproven",
      "family": "audit",
      "id": "SORRY-022",
      "note": "close via 3-witness consensus (NT+ALG+IT)"
    },
    {
      "source": "mathlib5/sorrydb",
      "status": "unproven",
      "family": "audit",
      "id": "SORRY-023",
      "note": "close via 3-witness consensus (NT+ALG+IT)"
    },
    {
      "source": "mathlib5/sorrydb",
      "status": "unproven",
      "family": "audit",
      "id": "SORRY-024",
      "note": "close via 3-witness consensus (NT+ALG+IT)"
    },
    {
      "source": "mathlib5/sorrydb",
      "status": "unproven",
      "family": "audit",
      "id": "SORRY-025",
      "note": "close via 3-witness consensus (NT+ALG+IT)"
    },
    {
      "source": "mathlib5/sorrydb",
      "status": "unproven",
      "family": "audit",
      "id": "SORRY-026",
      "note": "close via 3-witness consensus (NT+ALG+IT)"
    },
    {
      "source": "mathlib5/sorrydb",
      "status": "unproven",
      "family": "audit",
      "id": "SORRY-027",
      "note": "close via 3-witness consensus (NT+ALG+IT)"
    },
    {
      "source": "mathlib5/sorrydb",
      "status": "unproven",
      "family": "audit",
      "id": "SORRY-028",
      "note": "close via 3-witness consensus (NT+ALG+IT)"
    },
    {
      "source": "mathlib5/sorrydb",
      "status": "unproven",
      "family": "audit",
      "id": "SORRY-029",
      "note": "close via 3-witness consensus (NT+ALG+IT)"
    },
    {
      "source": "mathlib5/sorrydb",
      "status": "unproven",
      "family": "audit",
      "id": "SORRY-030",
      "note": "close via 3-witness consensus (NT+ALG+IT)"
    },
    {
      "source": "mathlib5/sorrydb",
      "status": "unproven",
      "family": "audit",
      "id": "SORRY-031",
      "note": "close via 3-witness consensus (NT+ALG+IT)"
    },
    {
      "source": "mathlib5/sorrydb",
      "status": "unproven",
      "family": "audit",
      "id": "SORRY-032",
      "note": "close via 3-witness consensus (NT+ALG+IT)"
    },
    {
      "source": "mathlib5/sorrydb",
      "status": "unproven",
      "family": "audit",
      "id": "SORRY-033",
      "note": "close via 3-witness consensus (NT+ALG+IT)"
    },
    {
      "source": "mathlib5/sorrydb",
      "status": "unproven",
      "family": "audit",
      "id": "SORRY-034",
      "note": "close via 3-witness consensus (NT+ALG+IT)"
    },
    {
      "source": "mathlib5/sorrydb",
      "status": "unproven",
      "family": "kernel",
      "id": "SORRY-035",
      "note": "close via 3-witness consensus (NT+ALG+IT)"
    },
    {
      "source": "mathlib5/sorrydb",
      "status": "unproven",
      "family": "kernel",
      "id": "SORRY-036",
      "note": "close via 3-witness consensus (NT+ALG+IT)"
    },
    {
      "source": "mathlib5/sorrydb",
      "status": "unproven",
      "family": "kernel",
      "id": "SORRY-037",
      "note": "close via 3-witness consensus (NT+ALG+IT)"
    },
    {
      "source": "mathlib5/sorrydb",
      "status": "unproven",
      "family": "kernel",
      "id": "SORRY-038",
      "note": "close via 3-witness consensus (NT+ALG+IT)"
    },
    {
      "source": "mathlib5/sorrydb",
      "status": "unproven",
      "family": "kernel",
      "id": "SORRY-039",
      "note": "close via 3-witness consensus (NT+ALG+IT)"
    },
    {
      "source": "mathlib5/sorrydb",
      "status": "unproven",
      "family": "kernel",
      "id": "SORRY-040",
      "note": "close via 3-witness consensus (NT+ALG+IT)"
    },
    {
      "source": "mathlib5/sorrydb",
      "status": "unproven",
      "family": "kernel",
      "id": "SORRY-041",
      "note": "close via 3-witness consensus (NT+ALG+IT)"
    },
    {
      "source": "mathlib5/sorrydb",
      "status": "unproven",
      "family": "kernel",
      "id": "SORRY-042",
      "note": "close via 3-witness consensus (NT+ALG+IT)"
    },
    {
      "source": "mathlib5/sorrydb",
      "status": "unproven",
      "family": "kernel",
      "id": "SORRY-043",
      "note": "close via 3-witness consensus (NT+ALG+IT)"
    },
    {
      "source": "mathlib5/sorrydb",
      "status": "unproven",
      "family": "kernel",
      "id": "SORRY-044",
      "note": "close via 3-witness consensus (NT+ALG+IT)"
    },
    {
      "source": "mathlib5/sorrydb",
      "status": "unproven",
      "family": "kernel",
      "id": "SORRY-045",
      "note": "close via 3-witness consensus (NT+ALG+IT)"
    },
    {
      "source": "mathlib5/sorrydb",
      "status": "unproven",
      "family": "kernel",
      "id": "SORRY-046",
      "note": "close via 3-witness consensus (NT+ALG+IT)"
    },
    {
      "source": "mathlib5/sorrydb",
      "status": "unproven",
      "family": "kernel",
      "id": "SORRY-047",
      "note": "close via 3-witness consensus (NT+ALG+IT)"
    },
    {
      "source": "mathlib5/sorrydb",
      "status": "unproven",
      "family": "kernel",
      "id": "SORRY-048",
      "note": "close via 3-witness consensus (NT+ALG+IT)"
    },
    {
      "source": "mathlib5/sorrydb",
      "status": "unproven",
      "family": "kernel",
      "id": "SORRY-049",
      "note": "close via 3-witness consensus (NT+ALG+IT)"
    },
    {
      "source": "mathlib5/sorrydb",
      "status": "unproven",
      "family": "kernel",
      "id": "SORRY-050",
      "note": "close via 3-witness consensus (NT+ALG+IT)"
    },
    {
      "source": "mathlib5/sorrydb",
      "status": "unproven",
      "family": "kernel",
      "id": "SORRY-051",
      "note": "close via 3-witness consensus (NT+ALG+IT)"
    },
    {
      "source": "mathlib5/sorrydb",
      "status": "unproven",
      "family": "kernel",
      "id": "SORRY-052",
      "note": "close via 3-witness consensus (NT+ALG+IT)"
    },
    {
      "source": "mathlib5/sorrydb",
      "status": "unproven",
      "family": "kernel",
      "id": "SORRY-053",
      "note": "close via 3-witness consensus (NT+ALG+IT)"
    },
    {
      "source": "mathlib5/sorrydb",
      "status": "unproven",
      "family": "kernel",
      "id": "SORRY-054",
      "note": "close via 3-witness consensus (NT+ALG+IT)"
    },
    {
      "source": "mathlib5/sorrydb",
      "status": "unproven",
      "family": "kernel",
      "id": "SORRY-055",
      "note": "close via 3-witness consensus (NT+ALG+IT)"
    },
    {
      "source": "mathlib5/sorrydb",
      "status": "unproven",
      "family": "kernel",
      "id": "SORRY-056",
      "note": "close via 3-witness consensus (NT+ALG+IT)"
    },
    {
      "source": "mathlib5/sorrydb",
      "status": "unproven",
      "family": "kernel",
      "id": "SORRY-057",
      "note": "close via 3-witness consensus (NT+ALG+IT)"
    },
    {
      "source": "mathlib5/sorrydb",
      "status": "unproven",
      "family": "kernel",
      "id": "SORRY-058",
      "note": "close via 3-witness consensus (NT+ALG+IT)"
    },
    {
      "source": "mathlib5/sorrydb",
      "status": "unproven",
      "family": "kernel",
      "id": "SORRY-059",
      "note": "close via 3-witness consensus (NT+ALG+IT)"
    },
    {
      "source": "mathlib5/sorrydb",
      "status": "unproven",
      "family": "kernel",
      "id": "SORRY-060",
      "note": "close via 3-witness consensus (NT+ALG+IT)"
    },
    {
      "source": "mathlib5/sorrydb",
      "status": "unproven",
      "family": "kernel",
      "id": "SORRY-061",
      "note": "close via 3-witness consensus (NT+ALG+IT)"
    },
    {
      "source": "mathlib5/sorrydb",
      "status": "unproven",
      "family": "kernel",
      "id": "SORRY-062",
      "note": "close via 3-witness consensus (NT+ALG+IT)"
    },
    {
      "source": "mathlib5/sorrydb",
      "status": "unproven",
      "family": "kernel",
      "id": "SORRY-063",
      "note": "close via 3-witness consensus (NT+ALG+IT)"
    },
    {
      "source": "mathlib5/sorrydb",
      "status": "unproven",
      "family": "kernel",
      "id": "SORRY-064",
      "note": "close via 3-witness consensus (NT+ALG+IT)"
    },
    {
      "source": "mathlib5/sorrydb",
      "status": "unproven",
      "family": "kernel",
      "id": "SORRY-065",
      "note": "close via 3-witness consensus (NT+ALG+IT)"
    },
    {
      "source": "mathlib5/sorrydb",
      "status": "unproven",
      "family": "kernel",
      "id": "SORRY-066",
      "note": "close via 3-witness consensus (NT+ALG+IT)"
    },
    {
      "source": "mathlib5/sorrydb",
      "status": "unproven",
      "family": "kernel",
      "id": "SORRY-067",
      "note": "close via 3-witness consensus (NT+ALG+IT)"
    },
    {
      "source": "mathlib5/sorrydb",
      "status": "unproven",
      "family": "kernel",
      "id": "SORRY-068",
      "note": "close via 3-witness consensus (NT+ALG+IT)"
    },
    {
      "source": "mathlib5/sorrydb",
      "status": "unproven",
      "family": "proofs",
      "id": "SORRY-069",
      "note": "close via 3-witness consensus (NT+ALG+IT)"
    },
    {
      "source": "mathlib5/sorrydb",
      "status": "unproven",
      "family": "proofs",
      "id": "SORRY-070",
      "note": "close via 3-witness consensus (NT+ALG+IT)"
    },
    {
      "source": "mathlib5/sorrydb",
      "status": "unproven",
      "family": "proofs",
      "id": "SORRY-071",
      "note": "close via 3-witness consensus (NT+ALG+IT)"
    },
    {
      "source": "mathlib5/sorrydb",
      "status": "unproven",
      "family": "proofs",
      "id": "SORRY-072",
      "note": "close via 3-witness consensus (NT+ALG+IT)"
    },
    {
      "source": "mathlib5/sorrydb",
      "status": "unproven",
      "family": "proofs",
      "id": "SORRY-073",
      "note": "close via 3-witness consensus (NT+ALG+IT)"
    },
    {
      "source": "mathlib5/sorrydb",
      "status": "unproven",
      "family": "proofs",
      "id": "SORRY-074",
      "note": "close via 3-witness consensus (NT+ALG+IT)"
    },
    {
      "source": "mathlib5/sorrydb",
      "status": "unproven",
      "family": "proofs",
      "id": "SORRY-075",
      "note": "close via 3-witness consensus (NT+ALG+IT)"
    },
    {
      "source": "mathlib5/sorrydb",
      "status": "unproven",
      "family": "proofs",
      "id": "SORRY-076",
      "note": "close via 3-witness consensus (NT+ALG+IT)"
    },
    {
      "source": "mathlib5/sorrydb",
      "status": "unproven",
      "family": "proofs",
      "id": "SORRY-077",
      "note": "close via 3-witness consensus (NT+ALG+IT)"
    },
    {
      "source": "mathlib5/sorrydb",
      "status": "unproven",
      "family": "proofs",
      "id": "SORRY-078",
      "note": "close via 3-witness consensus (NT+ALG+IT)"
    },
    {
      "source": "mathlib5/sorrydb",
      "status": "unproven",
      "family": "proofs",
      "id": "SORRY-079",
      "note": "close via 3-witness consensus (NT+ALG+IT)"
    },
    {
      "source": "mathlib5/sorrydb",
      "status": "unproven",
      "family": "proofs",
      "id": "SORRY-080",
      "note": "close via 3-witness consensus (NT+ALG+IT)"
    },
    {
      "source": "mathlib5/sorrydb",
      "status": "unproven",
      "family": "proofs",
      "id": "SORRY-081",
      "note": "close via 3-witness consensus (NT+ALG+IT)"
    },
    {
      "source": "mathlib5/sorrydb",
      "status": "unproven",
      "family": "proofs",
      "id": "SORRY-082",
      "note": "close via 3-witness consensus (NT+ALG+IT)"
    },
    {
      "source": "mathlib5/sorrydb",
      "status": "unproven",
      "family": "proofs",
      "id": "SORRY-083",
      "note": "close via 3-witness consensus (NT+ALG+IT)"
    },
    {
      "source": "mathlib5/sorrydb",
      "status": "unproven",
      "family": "proofs",
      "id": "SORRY-084",
      "note": "close via 3-witness consensus (NT+ALG+IT)"
    },
    {
      "source": "mathlib5/sorrydb",
      "status": "unproven",
      "family": "proofs",
      "id": "SORRY-085",
      "note": "close via 3-witness consensus (NT+ALG+IT)"
    },
    {
      "source": "mathlib5/sorrydb",
      "status": "unproven",
      "family": "proofs",
      "id": "SORRY-086",
      "note": "close via 3-witness consensus (NT+ALG+IT)"
    },
    {
      "source": "mathlib5/sorrydb",
      "status": "unproven",
      "family": "proofs",
      "id": "SORRY-087",
      "note": "close via 3-witness consensus (NT+ALG+IT)"
    },
    {
      "source": "mathlib5/sorrydb",
      "status": "unproven",
      "family": "proofs",
      "id": "SORRY-088",
      "note": "close via 3-witness consensus (NT+ALG+IT)"
    },
    {
      "source": "mathlib5/sorrydb",
      "status": "unproven",
      "family": "proofs",
      "id": "SORRY-089",
      "note": "close via 3-witness consensus (NT+ALG+IT)"
    },
    {
      "source": "mathlib5/sorrydb",
      "status": "unproven",
      "family": "proofs",
      "id": "SORRY-090",
      "note": "close via 3-witness consensus (NT+ALG+IT)"
    },
    {
      "source": "mathlib5/sorrydb",
      "status": "unproven",
      "family": "proofs",
      "id": "SORRY-091",
      "note": "close via 3-witness consensus (NT+ALG+IT)"
    },
    {
      "source": "mathlib5/sorrydb",
      "status": "unproven",
      "family": "proofs",
      "id": "SORRY-092",
      "note": "close via 3-witness consensus (NT+ALG+IT)"
    },
    {
      "source": "mathlib5/sorrydb",
      "status": "unproven",
      "family": "proofs",
      "id": "SORRY-093",
      "note": "close via 3-witness consensus (NT+ALG+IT)"
    },
    {
      "source": "mathlib5/sorrydb",
      "status": "unproven",
      "family": "proofs",
      "id": "SORRY-094",
      "note": "close via 3-witness consensus (NT+ALG+IT)"
    },
    {
      "source": "mathlib5/sorrydb",
      "status": "unproven",
      "family": "proofs",
      "id": "SORRY-095",
      "note": "close via 3-witness consensus (NT+ALG+IT)"
    },
    {
      "source": "mathlib5/sorrydb",
      "status": "unproven",
      "family": "proofs",
      "id": "SORRY-096",
      "note": "close via 3-witness consensus (NT+ALG+IT)"
    },
    {
      "source": "mathlib5/sorrydb",
      "status": "unproven",
      "family": "proofs",
      "id": "SORRY-097",
      "note": "close via 3-witness consensus (NT+ALG+IT)"
    },
    {
      "source": "mathlib5/sorrydb",
      "status": "unproven",
      "family": "proofs",
      "id": "SORRY-098",
      "note": "close via 3-witness consensus (NT+ALG+IT)"
    },
    {
      "source": "mathlib5/sorrydb",
      "status": "unproven",
      "family": "proofs",
      "id": "SORRY-099",
      "note": "close via 3-witness consensus (NT+ALG+IT)"
    },
    {
      "source": "mathlib5/sorrydb",
      "status": "unproven",
      "family": "proofs",
      "id": "SORRY-100",
      "note": "close via 3-witness consensus (NT+ALG+IT)"
    },
    {
      "source": "mathlib5/sorrydb",
      "status": "unproven",
      "family": "proofs",
      "id": "SORRY-101",
      "note": "close via 3-witness consensus (NT+ALG+IT)"
    },
    {
      "source": "mathlib5/sorrydb",
      "status": "unproven",
      "family": "proofs",
      "id": "SORRY-102",
      "note": "close via 3-witness consensus (NT+ALG+IT)"
    },
    {
      "source": "mathlib5/sorrydb",
      "status": "unproven",
      "family": "runtime",
      "id": "SORRY-103",
      "note": "close via 3-witness consensus (NT+ALG+IT)"
    },
    {
      "source": "mathlib5/sorrydb",
      "status": "unproven",
      "family": "runtime",
      "id": "SORRY-104",
      "note": "close via 3-witness consensus (NT+ALG+IT)"
    },
    {
      "source": "mathlib5/sorrydb",
      "status": "unproven",
      "family": "runtime",
      "id": "SORRY-105",
      "note": "close via 3-witness consensus (NT+ALG+IT)"
    },
    {
      "source": "mathlib5/sorrydb",
      "status": "unproven",
      "family": "runtime",
      "id": "SORRY-106",
      "note": "close via 3-witness consensus (NT+ALG+IT)"
    },
    {
      "source": "mathlib5/sorrydb",
      "status": "unproven",
      "family": "runtime",
      "id": "SORRY-107",
      "note": "close via 3-witness consensus (NT+ALG+IT)"
    },
    {
      "source": "mathlib5/sorrydb",
      "status": "unproven",
      "family": "runtime",
      "id": "SORRY-108",
      "note": "close via 3-witness consensus (NT+ALG+IT)"
    },
    {
      "source": "mathlib5/sorrydb",
      "status": "unproven",
      "family": "runtime",
      "id": "SORRY-109",
      "note": "close via 3-witness consensus (NT+ALG+IT)"
    },
    {
      "source": "mathlib5/sorrydb",
      "status": "unproven",
      "family": "runtime",
      "id": "SORRY-110",
      "note": "close via 3-witness consensus (NT+ALG+IT)"
    },
    {
      "source": "mathlib5/sorrydb",
      "status": "unproven",
      "family": "runtime",
      "id": "SORRY-111",
      "note": "close via 3-witness consensus (NT+ALG+IT)"
    },
    {
      "source": "mathlib5/sorrydb",
      "status": "unproven",
      "family": "runtime",
      "id": "SORRY-112",
      "note": "close via 3-witness consensus (NT+ALG+IT)"
    },
    {
      "source": "mathlib5/sorrydb",
      "status": "unproven",
      "family": "runtime",
      "id": "SORRY-113",
      "note": "close via 3-witness consensus (NT+ALG+IT)"
    },
    {
      "source": "mathlib5/sorrydb",
      "status": "unproven",
      "family": "runtime",
      "id": "SORRY-114",
      "note": "close via 3-witness consensus (NT+ALG+IT)"
    },
    {
      "source": "mathlib5/sorrydb",
      "status": "unproven",
      "family": "runtime",
      "id": "SORRY-115",
      "note": "close via 3-witness consensus (NT+ALG+IT)"
    },
    {
      "source": "mathlib5/sorrydb",
      "status": "unproven",
      "family": "runtime",
      "id": "SORRY-116",
      "note": "close via 3-witness consensus (NT+ALG+IT)"
    },
    {
      "source": "mathlib5/sorrydb",
      "status": "unproven",
      "family": "runtime",
      "id": "SORRY-117",
      "note": "close via 3-witness consensus (NT+ALG+IT)"
    },
    {
      "source": "mathlib5/sorrydb",
      "status": "unproven",
      "family": "runtime",
      "id": "SORRY-118",
      "note": "close via 3-witness consensus (NT+ALG+IT)"
    },
    {
      "source": "mathlib5/sorrydb",
      "status": "unproven",
      "family": "runtime",
      "id": "SORRY-119",
      "note": "close via 3-witness consensus (NT+ALG+IT)"
    },
    {
      "source": "mathlib5/sorrydb",
      "status": "unproven",
      "family": "runtime",
      "id": "SORRY-120",
      "note": "close via 3-witness consensus (NT+ALG+IT)"
    },
    {
      "source": "mathlib5/sorrydb",
      "status": "unproven",
      "family": "runtime",
      "id": "SORRY-121",
      "note": "close via 3-witness consensus (NT+ALG+IT)"
    },
    {
      "source": "mathlib5/sorrydb",
      "status": "unproven",
      "family": "runtime",
      "id": "SORRY-122",
      "note": "close via 3-witness consensus (NT+ALG+IT)"
    },
    {
      "source": "mathlib5/sorrydb",
      "status": "unproven",
      "family": "runtime",
      "id": "SORRY-123",
      "note": "close via 3-witness consensus (NT+ALG+IT)"
    },
    {
      "source": "mathlib5/sorrydb",
      "status": "unproven",
      "family": "runtime",
      "id": "SORRY-124",
      "note": "close via 3-witness consensus (NT+ALG+IT)"
    },
    {
      "source": "mathlib5/sorrydb",
      "status": "unproven",
      "family": "runtime",
      "id": "SORRY-125",
      "note": "close via 3-witness consensus (NT+ALG+IT)"
    },
    {
      "source": "mathlib5/sorrydb",
      "status": "unproven",
      "family": "runtime",
      "id": "SORRY-126",
      "note": "close via 3-witness consensus (NT+ALG+IT)"
    },
    {
      "source": "mathlib5/sorrydb",
      "status": "unproven",
      "family": "runtime",
      "id": "SORRY-127",
      "note": "close via 3-witness consensus (NT+ALG+IT)"
    },
    {
      "source": "mathlib5/sorrydb",
      "status": "unproven",
      "family": "runtime",
      "id": "SORRY-128",
      "note": "close via 3-witness consensus (NT+ALG+IT)"
    },
    {
      "source": "mathlib5/sorrydb",
      "status": "unproven",
      "family": "runtime",
      "id": "SORRY-129",
      "note": "close via 3-witness consensus (NT+ALG+IT)"
    },
    {
      "source": "mathlib5/sorrydb",
      "status": "unproven",
      "family": "runtime",
      "id": "SORRY-130",
      "note": "close via 3-witness consensus (NT+ALG+IT)"
    },
    {
      "source": "mathlib5/sorrydb",
      "status": "unproven",
      "family": "runtime",
      "id": "SORRY-131",
      "note": "close via 3-witness consensus (NT+ALG+IT)"
    },
    {
      "source": "mathlib5/sorrydb",
      "status": "unproven",
      "family": "runtime",
      "id": "SORRY-132",
      "note": "close via 3-witness consensus (NT+ALG+IT)"
    },
    {
      "source": "mathlib5/sorrydb",
      "status": "unproven",
      "family": "runtime",
      "id": "SORRY-133",
      "note": "close via 3-witness consensus (NT+ALG+IT)"
    },
    {
      "source": "mathlib5/sorrydb",
      "status": "unproven",
      "family": "runtime",
      "id": "SORRY-134",
      "note": "close via 3-witness consensus (NT+ALG+IT)"
    },
    {
      "source": "mathlib5/sorrydb",
      "status": "unproven",
      "family": "runtime",
      "id": "SORRY-135",
      "note": "close via 3-witness consensus (NT+ALG+IT)"
    },
    {
      "source": "mathlib5/sorrydb",
      "status": "unproven",
      "family": "runtime",
      "id": "SORRY-136",
      "note": "close via 3-witness consensus (NT+ALG+IT)"
    },
    {
      "source": "mathlib5/sorrydb",
      "status": "unproven",
      "family": "witnesses",
      "id": "SORRY-137",
      "note": "close via 3-witness consensus (NT+ALG+IT)"
    },
    {
      "source": "mathlib5/sorrydb",
      "status": "unproven",
      "family": "witnesses",
      "id": "SORRY-138",
      "note": "close via 3-witness consensus (NT+ALG+IT)"
    },
    {
      "source": "mathlib5/sorrydb",
      "status": "unproven",
      "family": "witnesses",
      "id": "SORRY-139",
      "note": "close via 3-witness consensus (NT+ALG+IT)"
    },
    {
      "source": "mathlib5/sorrydb",
      "status": "unproven",
      "family": "witnesses",
      "id": "SORRY-140",
      "note": "close via 3-witness consensus (NT+ALG+IT)"
    },
    {
      "source": "mathlib5/sorrydb",
      "status": "unproven",
      "family": "witnesses",
      "id": "SORRY-141",
      "note": "close via 3-witness consensus (NT+ALG+IT)"
    },
    {
      "source": "mathlib5/sorrydb",
      "status": "unproven",
      "family": "witnesses",
      "id": "SORRY-142",
      "note": "close via 3-witness consensus (NT+ALG+IT)"
    },
    {
      "source": "mathlib5/sorrydb",
      "status": "unproven",
      "family": "witnesses",
      "id": "SORRY-143",
      "note": "close via 3-witness consensus (NT+ALG+IT)"
    },
    {
      "source": "mathlib5/sorrydb",
      "status": "unproven",
      "family": "witnesses",
      "id": "SORRY-144",
      "note": "close via 3-witness consensus (NT+ALG+IT)"
    },
    {
      "source": "mathlib5/sorrydb",
      "status": "unproven",
      "family": "witnesses",
      "id": "SORRY-145",
      "note": "close via 3-witness consensus (NT+ALG+IT)"
    },
    {
      "source": "mathlib5/sorrydb",
      "status": "unproven",
      "family": "witnesses",
      "id": "SORRY-146",
      "note": "close via 3-witness consensus (NT+ALG+IT)"
    },
    {
      "source": "mathlib5/sorrydb",
      "status": "unproven",
      "family": "witnesses",
      "id": "SORRY-147",
      "note": "close via 3-witness consensus (NT+ALG+IT)"
    },
    {
      "source": "mathlib5/sorrydb",
      "status": "unproven",
      "family": "witnesses",
      "id": "SORRY-148",
      "note": "close via 3-witness consensus (NT+ALG+IT)"
    },
    {
      "source": "mathlib5/sorrydb",
      "status": "unproven",
      "family": "witnesses",
      "id": "SORRY-149",
      "note": "close via 3-witness consensus (NT+ALG+IT)"
    },
    {
      "source": "mathlib5/sorrydb",
      "status": "unproven",
      "family": "witnesses",
      "id": "SORRY-150",
      "note": "close via 3-witness consensus (NT+ALG+IT)"
    },
    {
      "source": "mathlib5/sorrydb",
      "status": "unproven",
      "family": "witnesses",
      "id": "SORRY-151",
      "note": "close via 3-witness consensus (NT+ALG+IT)"
    },
    {
      "source": "mathlib5/sorrydb",
      "status": "unproven",
      "family": "witnesses",
      "id": "SORRY-152",
      "note": "close via 3-witness consensus (NT+ALG+IT)"
    },
    {
      "source": "mathlib5/sorrydb",
      "status": "unproven",
      "family": "witnesses",
      "id": "SORRY-153",
      "note": "close via 3-witness consensus (NT+ALG+IT)"
    },
    {
      "source": "mathlib5/sorrydb",
      "status": "unproven",
      "family": "witnesses",
      "id": "SORRY-154",
      "note": "close via 3-witness consensus (NT+ALG+IT)"
    },
    {
      "source": "mathlib5/sorrydb",
      "status": "unproven",
      "family": "witnesses",
      "id": "SORRY-155",
      "note": "close via 3-witness consensus (NT+ALG+IT)"
    },
    {
      "source": "mathlib5/sorrydb",
      "status": "unproven",
      "family": "witnesses",
      "id": "SORRY-156",
      "note": "close via 3-witness consensus (NT+ALG+IT)"
    },
    {
      "source": "mathlib5/sorrydb",
      "status": "unproven",
      "family": "witnesses",
      "id": "SORRY-157",
      "note": "close via 3-witness consensus (NT+ALG+IT)"
    },
    {
      "source": "mathlib5/sorrydb",
      "status": "unproven",
      "family": "witnesses",
      "id": "SORRY-158",
      "note": "close via 3-witness consensus (NT+ALG+IT)"
    },
    {
      "source": "mathlib5/sorrydb",
      "status": "unproven",
      "family": "witnesses",
      "id": "SORRY-159",
      "note": "close via 3-witness consensus (NT+ALG+IT)"
    },
    {
      "source": "mathlib5/sorrydb",
      "status": "unproven",
      "family": "witnesses",
      "id": "SORRY-160",
      "note": "close via 3-witness consensus (NT+ALG+IT)"
    },
    {
      "source": "mathlib5/sorrydb",
      "status": "unproven",
      "family": "witnesses",
      "id": "SORRY-161",
      "note": "close via 3-witness consensus (NT+ALG+IT)"
    },
    {
      "source": "mathlib5/sorrydb",
      "status": "unproven",
      "family": "witnesses",
      "id": "SORRY-162",
      "note": "close via 3-witness consensus (NT+ALG+IT)"
    },
    {
      "source": "mathlib5/sorrydb",
      "status": "unproven",
      "family": "witnesses",
      "id": "SORRY-163",
      "note": "close via 3-witness consensus (NT+ALG+IT)"
    },
    {
      "source": "mathlib5/sorrydb",
      "status": "unproven",
      "family": "witnesses",
      "id": "SORRY-164",
      "note": "close via 3-witness consensus (NT+ALG+IT)"
    },
    {
      "source": "mathlib5/sorrydb",
      "status": "unproven",
      "family": "witnesses",
      "id": "SORRY-165",
      "note": "close via 3-witness consensus (NT+ALG+IT)"
    },
    {
      "source": "mathlib5/sorrydb",
      "status": "unproven",
      "family": "witnesses",
      "id": "SORRY-166",
      "note": "close via 3-witness consensus (NT+ALG+IT)"
    },
    {
      "source": "mathlib5/sorrydb",
      "status": "unproven",
      "family": "witnesses",
      "id": "SORRY-167",
      "note": "close via 3-witness consensus (NT+ALG+IT)"
    },
    {
      "source": "mathlib5/sorrydb",
      "status": "unproven",
      "family": "witnesses",
      "id": "SORRY-168",
      "note": "close via 3-witness consensus (NT+ALG+IT)"
    },
    {
      "source": "mathlib5/sorrydb",
      "status": "unproven",
      "family": "witnesses",
      "id": "SORRY-169",
      "note": "close via 3-witness consensus (NT+ALG+IT)"
    },
    {
      "source": "mathlib5/sorrydb",
      "status": "unproven",
      "family": "witnesses",
      "id": "SORRY-170",
      "note": "close via 3-witness consensus (NT+ALG+IT)"
    },
    {
      "source": "mathlib5/sorrydb",
      "status": "unproven",
      "family": "refinements",
      "id": "SORRY-171",
      "note": "close via 3-witness consensus (NT+ALG+IT)"
    },
    {
      "source": "mathlib5/sorrydb",
      "status": "unproven",
      "family": "refinements",
      "id": "SORRY-172",
      "note": "close via 3-witness consensus (NT+ALG+IT)"
    },
    {
      "source": "mathlib5/sorrydb",
      "status": "unproven",
      "family": "refinements",
      "id": "SORRY-173",
      "note": "close via 3-witness consensus (NT+ALG+IT)"
    },
    {
      "source": "mathlib5/sorrydb",
      "status": "unproven",
      "family": "refinements",
      "id": "SORRY-174",
      "note": "close via 3-witness consensus (NT+ALG+IT)"
    },
    {
      "source": "mathlib5/sorrydb",
      "status": "unproven",
      "family": "refinements",
      "id": "SORRY-175",
      "note": "close via 3-witness consensus (NT+ALG+IT)"
    },
    {
      "source": "mathlib5/sorrydb",
      "status": "unproven",
      "family": "refinements",
      "id": "SORRY-176",
      "note": "close via 3-witness consensus (NT+ALG+IT)"
    },
    {
      "source": "mathlib5/sorrydb",
      "status": "unproven",
      "family": "refinements",
      "id": "SORRY-177",
      "note": "close via 3-witness consensus (NT+ALG+IT)"
    },
    {
      "source": "mathlib5/sorrydb",
      "status": "unproven",
      "family": "refinements",
      "id": "SORRY-178",
      "note": "close via 3-witness consensus (NT+ALG+IT)"
    },
    {
      "source": "mathlib5/sorrydb",
      "status": "unproven",
      "family": "refinements",
      "id": "SORRY-179",
      "note": "close via 3-witness consensus (NT+ALG+IT)"
    },
    {
      "source": "mathlib5/sorrydb",
      "status": "unproven",
      "family": "refinements",
      "id": "SORRY-180",
      "note": "close via 3-witness consensus (NT+ALG+IT)"
    },
    {
      "source": "mathlib5/sorrydb",
      "status": "unproven",
      "family": "refinements",
      "id": "SORRY-181",
      "note": "close via 3-witness consensus (NT+ALG+IT)"
    },
    {
      "source": "mathlib5/sorrydb",
      "status": "unproven",
      "family": "refinements",
      "id": "SORRY-182",
      "note": "close via 3-witness consensus (NT+ALG+IT)"
    },
    {
      "source": "mathlib5/sorrydb",
      "status": "unproven",
      "family": "refinements",
      "id": "SORRY-183",
      "note": "close via 3-witness consensus (NT+ALG+IT)"
    },
    {
      "source": "mathlib5/sorrydb",
      "status": "unproven",
      "family": "refinements",
      "id": "SORRY-184",
      "note": "close via 3-witness consensus (NT+ALG+IT)"
    },
    {
      "source": "mathlib5/sorrydb",
      "status": "unproven",
      "family": "refinements",
      "id": "SORRY-185",
      "note": "close via 3-witness consensus (NT+ALG+IT)"
    },
    {
      "source": "mathlib5/sorrydb",
      "status": "unproven",
      "family": "refinements",
      "id": "SORRY-186",
      "note": "close via 3-witness consensus (NT+ALG+IT)"
    },
    {
      "source": "mathlib5/sorrydb",
      "status": "unproven",
      "family": "refinements",
      "id": "SORRY-187",
      "note": "close via 3-witness consensus (NT+ALG+IT)"
    },
    {
      "source": "mathlib5/sorrydb",
      "status": "unproven",
      "family": "refinements",
      "id": "SORRY-188",
      "note": "close via 3-witness consensus (NT+ALG+IT)"
    },
    {
      "source": "mathlib5/sorrydb",
      "status": "unproven",
      "family": "refinements",
      "id": "SORRY-189",
      "note": "close via 3-witness consensus (NT+ALG+IT)"
    },
    {
      "source": "mathlib5/sorrydb",
      "status": "unproven",
      "family": "refinements",
      "id": "SORRY-190",
      "note": "close via 3-witness consensus (NT+ALG+IT)"
    },
    {
      "source": "mathlib5/sorrydb",
      "status": "unproven",
      "family": "refinements",
      "id": "SORRY-191",
      "note": "close via 3-witness consensus (NT+ALG+IT)"
    },
    {
      "source": "mathlib5/sorrydb",
      "status": "unproven",
      "family": "refinements",
      "id": "SORRY-192",
      "note": "close via 3-witness consensus (NT+ALG+IT)"
    },
    {
      "source": "mathlib5/sorrydb",
      "status": "unproven",
      "family": "refinements",
      "id": "SORRY-193",
      "note": "close via 3-witness consensus (NT+ALG+IT)"
    },
    {
      "source": "mathlib5/sorrydb",
      "status": "unproven",
      "family": "refinements",
      "id": "SORRY-194",
      "note": "close via 3-witness consensus (NT+ALG+IT)"
    },
    {
      "source": "mathlib5/sorrydb",
      "status": "unproven",
      "family": "refinements",
      "id": "SORRY-195",
      "note": "close via 3-witness consensus (NT+ALG+IT)"
    },
    {
      "source": "mathlib5/sorrydb",
      "status": "unproven",
      "family": "refinements",
      "id": "SORRY-196",
      "note": "close via 3-witness consensus (NT+ALG+IT)"
    },
    {
      "source": "mathlib5/sorrydb",
      "status": "unproven",
      "family": "refinements",
      "id": "SORRY-197",
      "note": "close via 3-witness consensus (NT+ALG+IT)"
    },
    {
      "source": "mathlib5/sorrydb",
      "status": "unproven",
      "family": "refinements",
      "id": "SORRY-198",
      "note": "close via 3-witness consensus (NT+ALG+IT)"
    },
    {
      "source": "mathlib5/sorrydb",
      "status": "unproven",
      "family": "refinements",
      "id": "SORRY-199",
      "note": "close via 3-witness consensus (NT+ALG+IT)"
    },
    {
      "source": "mathlib5/sorrydb",
      "status": "unproven",
      "family": "refinements",
      "id": "SORRY-200",
      "note": "close via 3-witness consensus (NT+ALG+IT)"
    },
    {
      "source": "mathlib5/sorrydb",
      "status": "unproven",
      "family": "refinements",
      "id": "SORRY-201",
      "note": "close via 3-witness consensus (NT+ALG+IT)"
    },
    {
      "source": "mathlib5/sorrydb",
      "status": "unproven",
      "family": "refinements",
      "id": "SORRY-202",
      "note": "close via 3-witness consensus (NT+ALG+IT)"
    },
    {
      "source": "mathlib5/sorrydb",
      "status": "unproven",
      "family": "refinements",
      "id": "SORRY-203",
      "note": "close via 3-witness consensus (NT+ALG+IT)"
    },
    {
      "source": "mathlib5/sorrydb",
      "status": "unproven",
      "family": "refinements",
      "id": "SORRY-204",
      "note": "close via 3-witness consensus (NT+ALG+IT)"
    },
    {
      "source": "mathlib5/sorrydb",
      "status": "unproven",
      "family": "asp_gate",
      "id": "SORRY-205",
      "note": "close via 3-witness consensus (NT+ALG+IT)"
    },
    {
      "source": "mathlib5/sorrydb",
      "status": "unproven",
      "family": "asp_gate",
      "id": "SORRY-206",
      "note": "close via 3-witness consensus (NT+ALG+IT)"
    },
    {
      "source": "mathlib5/sorrydb",
      "status": "unproven",
      "family": "asp_gate",
      "id": "SORRY-207",
      "note": "close via 3-witness consensus (NT+ALG+IT)"
    },
    {
      "source": "mathlib5/sorrydb",
      "status": "unproven",
      "family": "asp_gate",
      "id": "SORRY-208",
      "note": "close via 3-witness consensus (NT+ALG+IT)"
    },
    {
      "source": "mathlib5/sorrydb",
      "status": "unproven",
      "family": "asp_gate",
      "id": "SORRY-209",
      "note": "close via 3-witness consensus (NT+ALG+IT)"
    },
    {
      "source": "mathlib5/sorrydb",
      "status": "unproven",
      "family": "asp_gate",
      "id": "SORRY-210",
      "note": "close via 3-witness consensus (NT+ALG+IT)"
    },
    {
      "source": "mathlib5/sorrydb",
      "status": "unproven",
      "family": "asp_gate",
      "id": "SORRY-211",
      "note": "close via 3-witness consensus (NT+ALG+IT)"
    },
    {
      "source": "mathlib5/sorrydb",
      "status": "unproven",
      "family": "asp_gate",
      "id": "SORRY-212",
      "note": "close via 3-witness consensus (NT+ALG+IT)"
    },
    {
      "source": "mathlib5/sorrydb",
      "status": "unproven",
      "family": "asp_gate",
      "id": "SORRY-213",
      "note": "close via 3-witness consensus (NT+ALG+IT)"
    },
    {
      "source": "mathlib5/sorrydb",
      "status": "unproven",
      "family": "asp_gate",
      "id": "SORRY-214",
      "note": "close via 3-witness consensus (NT+ALG+IT)"
    },
    {
      "source": "mathlib5/sorrydb",
      "status": "unproven",
      "family": "asp_gate",
      "id": "SORRY-215",
      "note": "close via 3-witness consensus (NT+ALG+IT)"
    },
    {
      "source": "mathlib5/sorrydb",
      "status": "unproven",
      "family": "asp_gate",
      "id": "SORRY-216",
      "note": "close via 3-witness consensus (NT+ALG+IT)"
    },
    {
      "source": "mathlib5/sorrydb",
      "status": "unproven",
      "family": "asp_gate",
      "id": "SORRY-217",
      "note": "close via 3-witness consensus (NT+ALG+IT)"
    },
    {
      "source": "mathlib5/sorrydb",
      "status": "unproven",
      "family": "asp_gate",
      "id": "SORRY-218",
      "note": "close via 3-witness consensus (NT+ALG+IT)"
    },
    {
      "source": "mathlib5/sorrydb",
      "status": "unproven",
      "family": "asp_gate",
      "id": "SORRY-219",
      "note": "close via 3-witness consensus (NT+ALG+IT)"
    },
    {
      "source": "mathlib5/sorrydb",
      "status": "unproven",
      "family": "asp_gate",
      "id": "SORRY-220",
      "note": "close via 3-witness consensus (NT+ALG+IT)"
    },
    {
      "source": "mathlib5/sorrydb",
      "status": "unproven",
      "family": "asp_gate",
      "id": "SORRY-221",
      "note": "close via 3-witness consensus (NT+ALG+IT)"
    },
    {
      "source": "mathlib5/sorrydb",
      "status": "unproven",
      "family": "asp_gate",
      "id": "SORRY-222",
      "note": "close via 3-witness consensus (NT+ALG+IT)"
    },
    {
      "source": "mathlib5/sorrydb",
      "status": "unproven",
      "family": "asp_gate",
      "id": "SORRY-223",
      "note": "close via 3-witness consensus (NT+ALG+IT)"
    },
    {
      "source": "mathlib5/sorrydb",
      "status": "unproven",
      "family": "asp_gate",
      "id": "SORRY-224",
      "note": "close via 3-witness consensus (NT+ALG+IT)"
    },
    {
      "source": "mathlib5/sorrydb",
      "status": "unproven",
      "family": "asp_gate",
      "id": "SORRY-225",
      "note": "close via 3-witness consensus (NT+ALG+IT)"
    },
    {
      "source": "mathlib5/sorrydb",
      "status": "unproven",
      "family": "asp_gate",
      "id": "SORRY-226",
      "note": "close via 3-witness consensus (NT+ALG+IT)"
    },
    {
      "source": "mathlib5/sorrydb",
      "status": "unproven",
      "family": "asp_gate",
      "id": "SORRY-227",
      "note": "close via 3-witness consensus (NT+ALG+IT)"
    },
    {
      "source": "mathlib5/sorrydb",
      "status": "unproven",
      "family": "asp_gate",
      "id": "SORRY-228",
      "note": "close via 3-witness consensus (NT+ALG+IT)"
    },
    {
      "source": "mathlib5/sorrydb",
      "status": "unproven",
      "family": "asp_gate",
      "id": "SORRY-229",
      "note": "close via 3-witness consensus (NT+ALG+IT)"
    },
    {
      "source": "mathlib5/sorrydb",
      "status": "unproven",
      "family": "asp_gate",
      "id": "SORRY-230",
      "note": "close via 3-witness consensus (NT+ALG+IT)"
    },
    {
      "source": "mathlib5/sorrydb",
      "status": "unproven",
      "family": "asp_gate",
      "id": "SORRY-231",
      "note": "close via 3-witness consensus (NT+ALG+IT)"
    },
    {
      "source": "mathlib5/sorrydb",
      "status": "unproven",
      "family": "asp_gate",
      "id": "SORRY-232",
      "note": "close via 3-witness consensus (NT+ALG+IT)"
    },
    {
      "source": "mathlib5/sorrydb",
      "status": "unproven",
      "family": "asp_gate",
      "id": "SORRY-233",
      "note": "close via 3-witness consensus (NT+ALG+IT)"
    },
    {
      "source": "mathlib5/sorrydb",
      "status": "unproven",
      "family": "asp_gate",
      "id": "SORRY-234",
      "note": "close via 3-witness consensus (NT+ALG+IT)"
    },
    {
      "source": "mathlib5/sorrydb",
      "status": "unproven",
      "family": "asp_gate",
      "id": "SORRY-235",
      "note": "close via 3-witness consensus (NT+ALG+IT)"
    },
    {
      "source": "mathlib5/sorrydb",
      "status": "unproven",
      "family": "asp_gate",
      "id": "SORRY-236",
      "note": "close via 3-witness consensus (NT+ALG+IT)"
    },
    {
      "source": "mathlib5/sorrydb",
      "status": "unproven",
      "family": "asp_gate",
      "id": "SORRY-237",
      "note": "close via 3-witness consensus (NT+ALG+IT)"
    },
    {
      "source": "mathlib5/sorrydb",
      "status": "unproven",
      "family": "asp_gate",
      "id": "SORRY-238",
      "note": "close via 3-witness consensus (NT+ALG+IT)"
    },
    {
      "source": "mathlib5/sorrydb",
      "status": "unproven",
      "family": "fol_engine",
      "id": "SORRY-239",
      "note": "close via 3-witness consensus (NT+ALG+IT)"
    },
    {
      "source": "mathlib5/sorrydb",
      "status": "unproven",
      "family": "fol_engine",
      "id": "SORRY-240",
      "note": "close via 3-witness consensus (NT+ALG+IT)"
    },
    {
      "source": "mathlib5/sorrydb",
      "status": "unproven",
      "family": "fol_engine",
      "id": "SORRY-241",
      "note": "close via 3-witness consensus (NT+ALG+IT)"
    },
    {
      "source": "mathlib5/sorrydb",
      "status": "unproven",
      "family": "fol_engine",
      "id": "SORRY-242",
      "note": "close via 3-witness consensus (NT+ALG+IT)"
    },
    {
      "source": "mathlib5/sorrydb",
      "status": "unproven",
      "family": "fol_engine",
      "id": "SORRY-243",
      "note": "close via 3-witness consensus (NT+ALG+IT)"
    },
    {
      "source": "mathlib5/sorrydb",
      "status": "unproven",
      "family": "fol_engine",
      "id": "SORRY-244",
      "note": "close via 3-witness consensus (NT+ALG+IT)"
    },
    {
      "source": "mathlib5/sorrydb",
      "status": "unproven",
      "family": "fol_engine",
      "id": "SORRY-245",
      "note": "close via 3-witness consensus (NT+ALG+IT)"
    },
    {
      "source": "mathlib5/sorrydb",
      "status": "unproven",
      "family": "fol_engine",
      "id": "SORRY-246",
      "note": "close via 3-witness consensus (NT+ALG+IT)"
    },
    {
      "source": "mathlib5/sorrydb",
      "status": "unproven",
      "family": "fol_engine",
      "id": "SORRY-247",
      "note": "close via 3-witness consensus (NT+ALG+IT)"
    },
    {
      "source": "mathlib5/sorrydb",
      "status": "unproven",
      "family": "fol_engine",
      "id": "SORRY-248",
      "note": "close via 3-witness consensus (NT+ALG+IT)"
    },
    {
      "source": "mathlib5/sorrydb",
      "status": "unproven",
      "family": "fol_engine",
      "id": "SORRY-249",
      "note": "close via 3-witness consensus (NT+ALG+IT)"
    },
    {
      "source": "mathlib5/sorrydb",
      "status": "unproven",
      "family": "fol_engine",
      "id": "SORRY-250",
      "note": "close via 3-witness consensus (NT+ALG+IT)"
    },
    {
      "source": "mathlib5/sorrydb",
      "status": "unproven",
      "family": "fol_engine",
      "id": "SORRY-251",
      "note": "close via 3-witness consensus (NT+ALG+IT)"
    },
    {
      "source": "mathlib5/sorrydb",
      "status": "unproven",
      "family": "fol_engine",
      "id": "SORRY-252",
      "note": "close via 3-witness consensus (NT+ALG+IT)"
    },
    {
      "source": "mathlib5/sorrydb",
      "status": "unproven",
      "family": "fol_engine",
      "id": "SORRY-253",
      "note": "close via 3-witness consensus (NT+ALG+IT)"
    },
    {
      "source": "mathlib5/sorrydb",
      "status": "unproven",
      "family": "fol_engine",
      "id": "SORRY-254",
      "note": "close via 3-witness consensus (NT+ALG+IT)"
    },
    {
      "source": "mathlib5/sorrydb",
      "status": "unproven",
      "family": "fol_engine",
      "id": "SORRY-255",
      "note": "close via 3-witness consensus (NT+ALG+IT)"
    },
    {
      "source": "mathlib5/sorrydb",
      "status": "unproven",
      "family": "fol_engine",
      "id": "SORRY-256",
      "note": "close via 3-witness consensus (NT+ALG+IT)"
    },
    {
      "source": "mathlib5/sorrydb",
      "status": "unproven",
      "family": "fol_engine",
      "id": "SORRY-257",
      "note": "close via 3-witness consensus (NT+ALG+IT)"
    },
    {
      "source": "mathlib5/sorrydb",
      "status": "unproven",
      "family": "fol_engine",
      "id": "SORRY-258",
      "note": "close via 3-witness consensus (NT+ALG+IT)"
    },
    {
      "source": "mathlib5/sorrydb",
      "status": "unproven",
      "family": "fol_engine",
      "id": "SORRY-259",
      "note": "close via 3-witness consensus (NT+ALG+IT)"
    },
    {
      "source": "mathlib5/sorrydb",
      "status": "unproven",
      "family": "fol_engine",
      "id": "SORRY-260",
      "note": "close via 3-witness consensus (NT+ALG+IT)"
    },
    {
      "source": "mathlib5/sorrydb",
      "status": "unproven",
      "family": "fol_engine",
      "id": "SORRY-261",
      "note": "close via 3-witness consensus (NT+ALG+IT)"
    },
    {
      "source": "mathlib5/sorrydb",
      "status": "unproven",
      "family": "fol_engine",
      "id": "SORRY-262",
      "note": "close via 3-witness consensus (NT+ALG+IT)"
    },
    {
      "source": "mathlib5/sorrydb",
      "status": "unproven",
      "family": "fol_engine",
      "id": "SORRY-263",
      "note": "close via 3-witness consensus (NT+ALG+IT)"
    },
    {
      "source": "mathlib5/sorrydb",
      "status": "unproven",
      "family": "fol_engine",
      "id": "SORRY-264",
      "note": "close via 3-witness consensus (NT+ALG+IT)"
    },
    {
      "source": "mathlib5/sorrydb",
      "status": "unproven",
      "family": "fol_engine",
      "id": "SORRY-265",
      "note": "close via 3-witness consensus (NT+ALG+IT)"
    },
    {
      "source": "mathlib5/sorrydb",
      "status": "unproven",
      "family": "fol_engine",
      "id": "SORRY-266",
      "note": "close via 3-witness consensus (NT+ALG+IT)"
    },
    {
      "source": "mathlib5/sorrydb",
      "status": "unproven",
      "family": "fol_engine",
      "id": "SORRY-267",
      "note": "close via 3-witness consensus (NT+ALG+IT)"
    },
    {
      "source": "mathlib5/sorrydb",
      "status": "unproven",
      "family": "fol_engine",
      "id": "SORRY-268",
      "note": "close via 3-witness consensus (NT+ALG+IT)"
    },
    {
      "source": "mathlib5/sorrydb",
      "status": "unproven",
      "family": "fol_engine",
      "id": "SORRY-269",
      "note": "close via 3-witness consensus (NT+ALG+IT)"
    },
    {
      "source": "mathlib5/sorrydb",
      "status": "unproven",
      "family": "fol_engine",
      "id": "SORRY-270",
      "note": "close via 3-witness consensus (NT+ALG+IT)"
    },
    {
      "source": "mathlib5/sorrydb",
      "status": "unproven",
      "family": "fol_engine",
      "id": "SORRY-271",
      "note": "close via 3-witness consensus (NT+ALG+IT)"
    },
    {
      "source": "mathlib5/sorrydb",
      "status": "unproven",
      "family": "fol_engine",
      "id": "SORRY-272",
      "note": "close via 3-witness consensus (NT+ALG+IT)"
    },
    {
      "source": "mathlib5/sorrydb",
      "status": "unproven",
      "family": "prism_skills",
      "id": "SORRY-273",
      "note": "close via 3-witness consensus (NT+ALG+IT)"
    },
    {
      "source": "mathlib5/sorrydb",
      "status": "unproven",
      "family": "prism_skills",
      "id": "SORRY-274",
      "note": "close via 3-witness consensus (NT+ALG+IT)"
    },
    {
      "source": "mathlib5/sorrydb",
      "status": "unproven",
      "family": "prism_skills",
      "id": "SORRY-275",
      "note": "close via 3-witness consensus (NT+ALG+IT)"
    },
    {
      "source": "mathlib5/sorrydb",
      "status": "unproven",
      "family": "prism_skills",
      "id": "SORRY-276",
      "note": "close via 3-witness consensus (NT+ALG+IT)"
    },
    {
      "source": "mathlib5/sorrydb",
      "status": "unproven",
      "family": "prism_skills",
      "id": "SORRY-277",
      "note": "close via 3-witness consensus (NT+ALG+IT)"
    },
    {
      "source": "mathlib5/sorrydb",
      "status": "unproven",
      "family": "prism_skills",
      "id": "SORRY-278",
      "note": "close via 3-witness consensus (NT+ALG+IT)"
    },
    {
      "source": "mathlib5/sorrydb",
      "status": "unproven",
      "family": "prism_skills",
      "id": "SORRY-279",
      "note": "close via 3-witness consensus (NT+ALG+IT)"
    },
    {
      "source": "mathlib5/sorrydb",
      "status": "unproven",
      "family": "prism_skills",
      "id": "SORRY-280",
      "note": "close via 3-witness consensus (NT+ALG+IT)"
    },
    {
      "source": "mathlib5/sorrydb",
      "status": "unproven",
      "family": "prism_skills",
      "id": "SORRY-281",
      "note": "close via 3-witness consensus (NT+ALG+IT)"
    },
    {
      "source": "mathlib5/sorrydb",
      "status": "unproven",
      "family": "prism_skills",
      "id": "SORRY-282",
      "note": "close via 3-witness consensus (NT+ALG+IT)"
    },
    {
      "source": "mathlib5/sorrydb",
      "status": "unproven",
      "family": "prism_skills",
      "id": "SORRY-283",
      "note": "close via 3-witness consensus (NT+ALG+IT)"
    },
    {
      "source": "mathlib5/sorrydb",
      "status": "unproven",
      "family": "prism_skills",
      "id": "SORRY-284",
      "note": "close via 3-witness consensus (NT+ALG+IT)"
    },
    {
      "source": "mathlib5/sorrydb",
      "status": "unproven",
      "family": "prism_skills",
      "id": "SORRY-285",
      "note": "close via 3-witness consensus (NT+ALG+IT)"
    },
    {
      "source": "mathlib5/sorrydb",
      "status": "unproven",
      "family": "prism_skills",
      "id": "SORRY-286",
      "note": "close via 3-witness consensus (NT+ALG+IT)"
    },
    {
      "source": "mathlib5/sorrydb",
      "status": "unproven",
      "family": "prism_skills",
      "id": "SORRY-287",
      "note": "close via 3-witness consensus (NT+ALG+IT)"
    },
    {
      "source": "mathlib5/sorrydb",
      "status": "unproven",
      "family": "prism_skills",
      "id": "SORRY-288",
      "note": "close via 3-witness consensus (NT+ALG+IT)"
    },
    {
      "source": "mathlib5/sorrydb",
      "status": "unproven",
      "family": "prism_skills",
      "id": "SORRY-289",
      "note": "close via 3-witness consensus (NT+ALG+IT)"
    },
    {
      "source": "mathlib5/sorrydb",
      "status": "unproven",
      "family": "prism_skills",
      "id": "SORRY-290",
      "note": "close via 3-witness consensus (NT+ALG+IT)"
    },
    {
      "source": "mathlib5/sorrydb",
      "status": "unproven",
      "family": "prism_skills",
      "id": "SORRY-291",
      "note": "close via 3-witness consensus (NT+ALG+IT)"
    },
    {
      "source": "mathlib5/sorrydb",
      "status": "unproven",
      "family": "prism_skills",
      "id": "SORRY-292",
      "note": "close via 3-witness consensus (NT+ALG+IT)"
    },
    {
      "source": "mathlib5/sorrydb",
      "status": "unproven",
      "family": "prism_skills",
      "id": "SORRY-293",
      "note": "close via 3-witness consensus (NT+ALG+IT)"
    },
    {
      "source": "mathlib5/sorrydb",
      "status": "unproven",
      "family": "prism_skills",
      "id": "SORRY-294",
      "note": "close via 3-witness consensus (NT+ALG+IT)"
    },
    {
      "source": "mathlib5/sorrydb",
      "status": "unproven",
      "family": "prism_skills",
      "id": "SORRY-295",
      "note": "close via 3-witness consensus (NT+ALG+IT)"
    },
    {
      "source": "mathlib5/sorrydb",
      "status": "unproven",
      "family": "prism_skills",
      "id": "SORRY-296",
      "note": "close via 3-witness consensus (NT+ALG+IT)"
    },
    {
      "source": "mathlib5/sorrydb",
      "status": "unproven",
      "family": "prism_skills",
      "id": "SORRY-297",
      "note": "close via 3-witness consensus (NT+ALG+IT)"
    },
    {
      "source": "mathlib5/sorrydb",
      "status": "unproven",
      "family": "prism_skills",
      "id": "SORRY-298",
      "note": "close via 3-witness consensus (NT+ALG+IT)"
    },
    {
      "source": "mathlib5/sorrydb",
      "status": "unproven",
      "family": "prism_skills",
      "id": "SORRY-299",
      "note": "close via 3-witness consensus (NT+ALG+IT)"
    },
    {
      "source": "mathlib5/sorrydb",
      "status": "unproven",
      "family": "prism_skills",
      "id": "SORRY-300",
      "note": "close via 3-witness consensus (NT+ALG+IT)"
    }
  ]
}